aws_lambda/__init__.py
aws_lambda/lambda_env_updater.py
aws_lambda/cloud_formation/__init__.py
aws_lambda/cloud_formation/lambda_aws_cdk.py
aws_lambda/cloud_formation/lambda_troposphere.py
aws_lambda/deployment/__init__.py
aws_lambda/deployment/deployment_package.py
aws_lambda/deployment/lambda_build.sh
aws_lambda/deployment/lambda_install.sh
aws_lambda/deployment/lambda_optimize.sh
aws_lambda/deployment/lambda_upload.sh
aws_lambda-2.1.3.dist-info/LICENSE.txt
aws_lambda-2.1.3.dist-info/METADATA
aws_lambda-2.1.3.dist-info/WHEEL
aws_lambda-2.1.3.dist-info/top_level.txt
aws_lambda-2.1.3.dist-info/RECORD
