Metadata-Version: 2.1
Name: aws-lambda
Version: 2.1.3
Summary: Package which helps to do various actions associated with AWS Lambda functions.
Home-page: https://github.com/laimonassutkus/AwsLambda
Author: Laimonas Sutkus
Author-email: laimonas.sutkus@gmail.com
License: GNU GENERAL PUBLIC LICENSE Version 3
Keywords: AWS CDK CloudFormation Troposphere Lambda Infrastructure Cloud DevOps DeploymentPackage
Platform: UNKNOWN
Classifier: Programming Language :: Python :: 3
Classifier: Programming Language :: Python :: 3.5
Classifier: Programming Language :: Python :: 3.6
Classifier: Programming Language :: Python :: 3.7
Classifier: Programming Language :: Python :: 3.8
Classifier: Operating System :: OS Independent
Requires-Dist: boto3
Requires-Dist: botocore
Requires-Dist: troposphere
Requires-Dist: aws-cdk.core
Requires-Dist: aws-cdk.aws-iam
Requires-Dist: aws-cdk.aws-ec2
Requires-Dist: aws-cdk.aws-lambda
Requires-Dist: cfnresponse
